ndn/__init__.py
ndn/app.py
ndn/app_support/__init__.py
ndn/app_support/dispatcher.py
ndn/app_support/ecies.py
ndn/app_support/keychain_register.py
ndn/app_support/light_versec/__init__.py
ndn/app_support/light_versec/binary.py
ndn/app_support/light_versec/checker.py
ndn/app_support/light_versec/compiler.py
ndn/app_support/light_versec/grammar.py
ndn/app_support/light_versec/parser.py
ndn/app_support/light_versec/validator.py
ndn/app_support/nfd_mgmt.py
ndn/app_support/security_v2.py
ndn/app_support/segment_fetcher.py
ndn/app_support/svs/__init__.py
ndn/app_support/svs/sync.py
ndn/app_support/svs/tlv.py
ndn/appv2.py
ndn/bin/__init__.py
ndn/bin/nfdc/__init__.py
ndn/bin/nfdc/__main__.py
ndn/bin/nfdc/cmd_get_face.py
ndn/bin/nfdc/cmd_get_route.py
ndn/bin/nfdc/cmd_get_status.py
ndn/bin/nfdc/cmd_get_strategy.py
ndn/bin/nfdc/cmd_new_face.py
ndn/bin/nfdc/cmd_new_route.py
ndn/bin/nfdc/cmd_remove_face.py
ndn/bin/nfdc/cmd_remove_route.py
ndn/bin/nfdc/cmd_remove_strategy.py
ndn/bin/nfdc/cmd_set_strategy.py
ndn/bin/nfdc/utils.py
ndn/bin/sec/__init__.py
ndn/bin/sec/__main__.py
ndn/bin/sec/cmd_export_cert.py
ndn/bin/sec/cmd_get_childitem.py
ndn/bin/sec/cmd_get_default.py
ndn/bin/sec/cmd_get_signreq.py
ndn/bin/sec/cmd_import_cert.py
ndn/bin/sec/cmd_init_pib.py
ndn/bin/sec/cmd_new_item.py
ndn/bin/sec/cmd_remove_item.py
ndn/bin/sec/cmd_set_default.py
ndn/bin/sec/cmd_sign_cert.py
ndn/bin/sec/utils.py
ndn/bin/tools/__init__.py
ndn/bin/tools/__main__.py
ndn/bin/tools/cmd_compile_lvs.py
ndn/bin/tools/cmd_fetch_data.py
ndn/bin/tools/cmd_fetch_rdrcontent.py
ndn/bin/tools/cmd_serve_data.py
ndn/bin/tools/cmd_serve_rdrcontent.py
ndn/client_conf.py
ndn/contrib/__init__.py
ndn/contrib/boost_info/__init__.py
ndn/contrib/boost_info/parser.py
ndn/contrib/cocoapy/LICENSE
ndn/contrib/cocoapy/__init__.py
ndn/contrib/cocoapy/cocoalibs.py
ndn/contrib/cocoapy/cocoatypes.py
ndn/contrib/cocoapy/runtime.py
ndn/encoding/__init__.py
ndn/encoding/name/Component.py
ndn/encoding/name/Name.py
python_ndn-0.5.1.dist-info/AUTHORS.rst
python_ndn-0.5.1.dist-info/COPYING
python_ndn-0.5.1.dist-info/METADATA
python_ndn-0.5.1.dist-info/WHEEL
python_ndn-0.5.1.dist-info/entry_points.txt
python_ndn-0.5.1.dist-info/RECORD
