Metadata-Version: 2.1
Name: python-ndn
Version: 0.5.1
Summary: An NDN client library with AsyncIO support in Python 3
Home-page: https://python-ndn.readthedocs.io
License: Apache-2.0
Keywords: NDN
Author: Xinyu Ma
Author-email: ma.xinyu.26a@kyoto-u.jp
Requires-Python: >=3.10,<4.0
Classifier: Development Status :: 4 - Beta
Classifier: Intended Audience :: Developers
Classifier: License :: OSI Approved :: Apache Software License
Classifier: Programming Language :: Python :: 3
Classifier: Programming Language :: Python :: 3.10
Classifier: Programming Language :: Python :: 3.11
Classifier: Programming Language :: Python :: 3.12
Classifier: Programming Language :: Python :: 3.13
Classifier: Topic :: Internet
Classifier: Topic :: Software Development :: Libraries
Classifier: Topic :: System :: Networking
Provides-Extra: dev
Provides-Extra: docs
Requires-Dist: Sphinx (>=7.1.2,<8.0.0) ; extra == "docs"
Requires-Dist: aenum (>=3.1.15,<4.0.0)
Requires-Dist: aiohttp (>=3.10.9,<4.0.0)
Requires-Dist: flake8 (>=6.1.0,<7.0.0) ; extra == "dev"
Requires-Dist: lark (>=1.2.2,<2.0.0)
Requires-Dist: pycryptodomex (>=3.21.0,<4.0.0)
Requires-Dist: pygtrie (>=2.5.0,<3.0.0)
Requires-Dist: pytest (>=7.1.2,<8.0.0) ; extra == "dev"
Requires-Dist: pytest-cov (>=4.1.0,<5.0.0) ; extra == "dev"
Requires-Dist: sphinx-autodoc-typehints (>=1.24.0,<2.0.0) ; extra == "docs"
Requires-Dist: sphinx-rtd-theme (>=1.3.0rc1,<2.0.0) ; extra == "docs"
Project-URL: Bug Tracker, https://github.com/named-data/python-ndn/issues
Project-URL: Changelog, https://python-ndn.readthedocs.io/en/latest/src/changelog.html
Project-URL: Documentation, https://python-ndn.readthedocs.io
Project-URL: Repository, https://github.com/named-data/python-ndn
